iwiki/__init__.py
iwiki/tests.py
iwiki/wiki.py
iwiki-0.0.1.dist-info/LICENSE
iwiki-0.0.1.dist-info/METADATA
iwiki-0.0.1.dist-info/WHEEL
iwiki-0.0.1.dist-info/top_level.txt
iwiki-0.0.1.dist-info/RECORD
