Metadata-Version: 2.1
Name: iwiki
Version: 0.0.1
Summary: innovata-wiki
Home-page: https://github.com/innovata/iwiki
Author: innovata sambong
Author-email: iinnovata@gmail.com
License: UNKNOWN
Platform: UNKNOWN
Classifier: Programming Language :: Python :: 3
Classifier: License :: OSI Approved :: MIT License
Classifier: Operating System :: OS Independent
